README.md
setup.cfg
setup.py
pydbro/_version.py
pydbro/coned.py
pydbro/dbro.py
pydbro/py_break_handler.py
pydbro/py_cfg.py
pydbro/py_cmd_params.py
pydbro/py_curses_lib.py
pydbro/py_error_handler.py
pydbro/py_get_list_vals.py
pydbro/py_key_moves.py
pydbro/py_list_to_str.py
pydbro/py_log.py
pydbro/py_mysql_db.py
pydbro/py_ora_db.py
pydbro/py_postgres_db.py
pydbro/py_prn_list.py
pydbro/py_qry.py
pydbro/py_read_str.py
pydbro/py_sel_list.py
pydbro/py_sqlite_db.py
pydbro/py_ugetch.py
pydbro.egg-info/PKG-INFO
pydbro.egg-info/SOURCES.txt
pydbro.egg-info/dependency_links.txt
pydbro.egg-info/entry_points.txt
pydbro.egg-info/top_level.txt