Metadata-Version: 2.1
Name: pydbro
Version: 0.1.16
Summary: Python Console Database Browser
Home-page: https://github.com/mtatton/pydbro
Author: Michael Tatton
Classifier: Development Status :: 1 - Planning
Classifier: Intended Audience :: Developers
Classifier: Topic :: Software Development :: User Interfaces
Classifier: Operating System :: POSIX :: Linux
Classifier: Programming Language :: Python :: 3.7
